<?xml version="1.0" encoding="UTF-8"?><i><chatserver>chat.bilibili.com</chatserver><chatid>3336924</chatid><mission>0</mission><maxlimit>3000</maxlimit><state>0</state><real_name>0</real_name><source>DF</source><d p="1317.20300,1,25,6830715,1523643857,0,14b237a6,4458510074">飞镖 发表 风暴 方便 反驳 副本 分贝 犯病？啊！犯病！</d><d p="699.22000,1,25,16777215,1523674103,0,1c60fe92,4458956876">经济来源不是真由理吗？</d><d p="268.23000,1,25,16777215,1523678561,0,1a19d1a9,4459127094">K 的梗啊</d><d p="445.00600,1,25,16777215,1523683856,0,a6d2cfad,4459382413">嘟嘟噜</d><d p="166.56000,1,25,16777215,1523687605,0,24299703,4459541949">诺基亚6无压力</d><d p="508.12600,5,25,16777215,1523692535,0,9df0b191,4459735554">花泽香肠</d><d p="389.78000,1,25,16777215,1523697737,0,1b0faa83,4459967652">好一个命名师</d><d p="461.73600,1,25,16777215,1523702484,0,c0d7818a,4460188462">嘟嘟噜</d><d p="300.11200,1,25,16777215,1523703901,0,da8bdeaf,4460257276">都是时辰的错</d><d p="779.72300,1,25,16777215,1523706553,0,da8bdeaf,4460406221">偷税</d><d p="1005.64300,1,25,16777215,1523707050,0,da8bdeaf,4460432052">白绝</d><d p="39.28100,1,25,16777215,1523707088,0,47aaf544,4460433979">R=RNG</d><d p="167.38500,1,25,16777215,1523707360,0,47aaf544,4460448239">黑暗料理</d><d p="1038.48900,1,25,16777215,1523708352,0,47aaf544,4460500896">事件视界啊</d><d p="1059.04900,1,25,16777215,1523708385,0,47aaf544,4460502555">永恒时空啊</d><d p="1102.01000,1,25,16777215,1523708444,0,47aaf544,4460505518">赛尔号的你坐下</d><d p="1062.15600,1,25,16777215,1523709430,0,27e5819b,4460557185">小软</d><d p="1150.51200,1,25,16777215,1523710006,0,2d875854,4460587757">不能让她看啊！！</d><d p="61.18200,1,25,16777215,1523710349,0,d373c0fe,4460606347">放屁明明我干的。</d><d p="185.36300,1,25,16777215,1523710398,0,d373c0fe,4460609031">蛋碎了一地。</d><d p="211.92400,1,25,16777215,1523710438,0,d373c0fe,4460611154">霸王餐</d><d p="244.18000,1,25,16777215,1523710486,0,d373c0fe,4460613715">日本好小，那么容易就全员到齐</d><d p="582.07900,1,25,16777215,1523710662,0,d373c0fe,4460623317">这逼装的满分</d><d p="608.93800,1,25,16777215,1523710711,0,d373c0fe,4460626112">哈哈哈哈</d><d p="724.01000,1,25,16777215,1523710750,0,d373c0fe,4460628185">大胸妹！！！</d><d p="777.96200,1,25,16777215,1523710798,0,d373c0fe,4460630768">发型满分</d><d p="672.83700,1,25,16777215,1523711199,0,637eb54a,4460652636">漏漏漏</d><d p="1261.20300,1,25,16777215,1523713405,0,fc4c394d,4460776102">吉尔伽美什：杂修，本王的语言库里没有这句话</d><d p="39.85800,1,25,16777215,1523718956,0,397b5ca7,4461102527">我竟然稳住了</d><d p="1077.50500,1,25,16777215,1523719005,0,4c1d08c,4461105314">原来我这么晚才看这部番，我是2020</d><d p="934.34000,1,25,16777215,1523720417,0,a0b1370,4461185508">heitai</d><d p="951.04000,1,25,16777215,1523720435,0,a0b1370,4461186447">hentai</d><d p="775.59800,1,25,16777215,1523729180,0,d94c19c1,4461519732">糟糕的台词</d><d p="928.99800,1,25,16777215,1523733535,0,46420327,4461587906">那就用二进制发啊</d><d p="538.28800,1,25,16777215,1523761775,0,ee6466c9,4462079169">花泽空心菜</d><d p="512.93800,1,25,16777215,1523762379,0,e06ddb7,4462104562">一看内你系咯（你们够了）</d><d p="510.51100,1,25,16777215,1523764179,0,b0191e04,4462181435">好雞兒無聊呀</d><d p="1304.76900,1,25,16777215,1523766432,0,fe7fecdf,4462287497">Flashback?</d><d p="1135.62000,1,25,16707842,1523766778,0,96701c6f,4462304706">绝望先生有个女孩也是只能发短信不说话</d><d p="1338.74500,1,25,16776960,1523767110,0,be93e835,4462321663">fly b..蝴蝶</d><d p="534.05900,1,25,16707842,1523768330,0,65ba2232,4462384749">心疼王一秒</d><d p="394.68900,5,25,16707842,1523771616,0,8cd25389,4462553612">圆桌会议啊！老哥！</d><d p="503.02900,5,25,16707842,1523771739,0,8cd25389,4462559438">花泽紫菜</d><d p="504.54900,5,25,16707842,1523771748,0,8cd25389,4462559800">花泽香肠</d><d p="754.25100,5,25,16707842,1523772002,0,8cd25389,4462571505">脱衣女</d><d p="695.85300,1,25,16777215,1523774695,0,5b0088d5,4462688598">黑了人家系统那么久，现在才想危险问题嘛？</d><d p="1064.54300,1,25,16777215,1523775588,0,e99c4f29,4462726187">太暴力了</d><d p="1044.66000,1,25,14811775,1523776163,0,271493c2,4462749852">事件视界阿</d><d p="270.24000,1,25,16777215,1523784263,0,256550c5,4463088713">好想帮她把衣服穿好啊</d><d p="1320.20600,1,25,16777215,1523787461,0,7ecf1747,4463219202">这么草率的吗？</d><d p="1207.81600,1,25,16777215,1523789686,0,681a3301,4463311074">眯眯眼的都是怪物</d><d p="438.38100,1,25,16777215,1523791285,0,872e2e39,4463378145">开始认真探讨命名了啊。。。</d><d p="1348.20200,1,25,16777215,1523794969,0,b7c2c199,4463534821">gg</d><d p="500.48400,5,25,16777215,1523795601,0,1e7b2ab,4463562238">花泽榨菜</d><d p="22.28100,1,25,16777215,1523798860,0,b052d34e,4463709490">我花了六个月看到这了</d><d p="817.61600,1,25,16777215,1523799700,0,b052d34e,4463749457">应该是未来吧</d><d p="1263.44500,1,25,16777215,1523805677,0,3520b83e,4464048766">凉凉，要是主角不灭口那就真的凉凉</d><d p="974.72200,1,25,16777215,1523809424,0,a32fb5d5,4464209568">戴冠之时已至，其为始动万象之理</d><d p="436.86300,1,25,16777215,1523811310,0,8555c6ba,4464267060">其实还是冈轮的最浪漫</d><d p="1327.52500,1,25,16777215,1523839871,0,6cce34e7,4464542470">衣服就不能穿好来</d><d p="398.05600,1,25,41194,1523840504,0,389239aa,4464550257">区区一个红莉栖</d><d p="507.98900,1,25,16777215,1523844476,0,2b97d789,4464605161">花泽兵北库</d><d p="699.77100,1,25,16777215,1523844687,0,2b97d789,4464608290">绿到我了</d><d p="756.41100,1,25,16777215,1523849848,0,6c80f799,4464733450">Enuma Elish</d><d p="438.27200,1,25,16777215,1523852907,0,b70a362d,4464808618">时光回溯</d><d p="1222.98200,1,25,16777215,1523855736,0,6487a301,4464915053">欧根亲王</d><d p="528.65200,1,25,16777215,1523868397,0,b1a8e998,4465218773">花泽油麦菜</d><d p="302.18000,1,25,16777215,1523879147,0,4a387b27,4465559791">话说他们从来不换衣服啊</d><d p="329.24800,1,25,16777215,1523880604,0,2dc29a38,4465621512">问题是下面那妹子从头听到尾啊QAQ</d><d p="331.66800,1,25,16777215,1523880616,0,2dc29a38,4465621964">谁去关窗户QAQ</d><d p="377.05700,1,25,16777215,1523880691,0,2dc29a38,4465624776">是香菜哦</d><d p="486.24800,1,25,16777215,1523880823,0,2dc29a38,4465629777">因为他们弄不清楚QAQ</d><d p="589.48800,1,25,16777215,1523880967,0,2dc29a38,4465635129">想起核爆</d><d p="989.74800,1,25,16777215,1523881426,0,2dc29a38,4465661214">别人家的高科技</d><d p="995.76800,1,25,16777215,1523881447,0,2dc29a38,4465662043">因为你家的微波炉不是主角造的</d><d p="1074.78800,1,25,16777215,1523881541,0,2dc29a38,4465665713">一瞬即永远，一线即世界</d><d p="1090.60800,1,25,16777215,1523881576,0,2dc29a38,4465667110">未来若可逆，时间何选择?</d><d p="1204.22900,1,25,16777215,1523881696,0,2dc29a38,4465671779">借了会怎么样？</d><d p="796.94300,1,25,16777215,1523883849,0,383bfdac,4465756738">帽子的图案 恩~~</d><d p="231.09400,1,25,16777215,1523887352,0,9c22ff43,4465912647">这辈分。。。。</d><d p="655.92800,1,25,16777215,1523887811,0,9c22ff43,4465934197">助手，你算计我！</d><d p="860.29400,1,25,16777215,1523890042,0,7cf7fc99,4466040347">你以为店长是正常人，搞笑</d><d p="1268.07200,1,25,16777215,1523890468,0,7cf7fc99,4466060253">唉，不让她知道就好了</d><d p="391.60900,1,25,16777215,1523896218,0,29e96f4a,4466293271">好羞耻</d><d p="425.53600,1,25,15138834,1523896541,0,e1fe2feb,4466302331">逆时间邮件不就OK了？</d><d p="830.49900,1,25,16777215,1523924455,0,925b4a09,4466550389">剧场版可以看看</d><d p="1322.92200,1,25,16777215,1523924990,0,925b4a09,4466556553">Z罗Z罗狗裆</d><d p="263.73800,1,25,16777215,1523930990,0,b84eeb5d,4466633321">香菜好吃</d><d p="519.43000,1,25,16777215,1523931257,0,b84eeb5d,4466637264">你们够了</d><d p="775.47000,1,25,16777215,1523931513,0,b84eeb5d,4466641087">哈哈哈哈哈恍恍惚惚好</d><d p="802.59500,1,25,16777215,1523942912,0,7b0bb583,4466953417">似李  学院长</d><d p="1144.84200,1,25,16777215,1523956143,0,1279fa9a,4467234376">男主略尬</d><d p="816.98400,1,25,16777215,1523957313,0,cd59792e,4467263737">未来完成时态是什么</d><d p="36.84400,1,25,16777215,1523958034,0,c0a878e0,4467282899">蒙逼了6集</d><d p="311.16500,1,25,16777011,1523960878,0,75f8ab78,4467535095">喊我老婆干嘛</d><d p="1268.93800,1,25,16777215,1523967249,0,e1fe2feb,4467761057">实力卖队友</d><d p="546.73500,1,25,16777215,1523972177,0,52fb7c08,4467965838">花泽泡菜</d><d p="561.19900,5,25,26112,1523972192,0,52fb7c08,4467966482">花泽泡菜</d><d p="514.95000,1,25,16777215,1523978097,0,62bbaeb5,4468259246">你们停吧</d><d p="434.18100,1,25,16777215,1523993222,0,611b614d,4468590072">溯朔</d><d p="37.59000,1,25,15138834,1524026489,0,49da6514,4468983976">少女好手速</d><d p="383.36900,1,25,15138834,1524026788,0,49da6514,4468994813">幺儿零吗，这里有人疯了</d><d p="233.85100,1,25,16777215,1524029473,0,ac2b41bf,4469085631">嘟嘟噜</d><d p="837.24900,1,25,16777215,1524034474,0,17042bf9,4469194770">看这个是真滴困啊</d><d p="1.19300,1,25,16777215,1524040805,0,883e1afe,4469317686">终于可以开始新的一集了</d><d p="28.09700,1,25,16777215,1524047072,0,24f77abd,4469502842">到底在讲什么</d><d p="264.80200,5,25,16707842,1524050500,0,b77520a9,4469623904">唔姆</d><d p="427.92300,1,25,16777215,1524055779,0,ae64bd13,4469817957">垮越海峡的生命桥</d><d p="473.99100,1,25,16777215,1524060593,0,18122af,4470028387">(仮)</d><d p="1281.44200,1,25,16777215,1524062334,0,46a01252,4470109081">他这些中二反应反而让指压师更加警惕</d><d p="458.65800,1,25,16777215,1524063347,0,8e562e57,4470157299">哈哈哈哈回到未来梗</d><d p="12.29100,1,25,16777215,1524064003,0,d2d9e777,4470187845">本集高能</d><d p="728.81100,5,25,15138834,1524069773,0,9fd0efee,4470410710">脱衣女是你吗？</d><d p="862.36700,5,25,16707842,1524078645,0,8565115a,4470545790">抱歉，这番里面除了路人，露过脸的都是重要人物233</d><d p="1250.12700,5,25,16707842,1524079070,0,8565115a,4470549024">GGGGGGG 游戏结束，悲剧的开始  起因</d><d p="1324.40700,5,25,16707842,1524079161,0,8565115a,4470549662">25崽啊</d><d p="269.35400,5,25,16777215,1524105731,0,2b1371c,4470780199">亚瑟王的圆桌骑士？</d><d p="243.80100,1,25,16777215,1524107376,0,b6f2614b,4470810687">抓到请客的</d><d p="274.31600,1,25,16777215,1524129840,0,150888e7,4471370807">呼叫小白！矮脚桌会议！</d><d p="935.53400,1,25,16777215,1524136825,0,cd9bbc1c,4471600412">糟糕的台词</d><d p="1269.28300,1,25,16777215,1524137533,0,cd9bbc1c,4471633658">GG</d><d p="1325.19900,1,25,16777215,1524141733,0,b26b5b2,4471794121">放屁</d><d p="416.50200,1,25,15138834,1524144158,0,acf01cf4,4471892912">少数服从多数</d><d p="241.16800,1,25,16777215,1524147726,0,ff201f87,4472055731">我有嘟嘟噜这首歌‘’</d><d p="297.08900,5,25,41194,1524148093,0,824fcc1c,4472073294">不愧是闪闪</d><d p="701.12700,5,25,9487136,1524148613,0,824fcc1c,4472098256">古天落绿了！！</d><d p="783.32600,5,25,14811775,1524148713,0,824fcc1c,4472103083">玛茵我的</d><d p="1146.83000,5,25,11890,1524149027,0,824fcc1c,4472118681">没错有头的塞姐</d><d p="314.92000,1,25,16777215,1524150248,0,76210da2,4472179596">杂修</d><d p="781.35300,1,25,16777215,1524150739,0,76210da2,4472203802">很愉悦啊</d><d p="164.94800,1,25,16777215,1524152373,0,f53468c8,4472280927">魅蓝x    16nm    p20</d><d p="391.16700,1,25,16777215,1524152666,0,f53468c8,4472293677">小时候，乡愁是一枚小小的邮票</d><d p="225.86900,5,25,16707842,1524158832,0,31ee7a71,4472481741">一拳一个嘟嘟噜怪</d><d p="8.88800,1,25,16777215,1524203040,0,9db34b47,4473166873">人类荣光永存！</d><d p="1267.45300,1,25,16777215,1524204411,0,e9cd99f,4473209986">完蛋了</d><d p="317.70300,5,25,255,1524211663,0,eb35f544,4473387118">吾王礼司，剑统万宗</d><d p="215.98700,1,25,16777215,1524212575,0,c4be26cf,4473410131">，，，，，，</d><d p="231.10100,5,25,41194,1524222142,0,aa35a7e0,4473752877">嘟嘟噜</d><d p="595.13500,5,18,41194,1524225831,0,dd0d4adc,4473917662">雷电法王</d><d p="1256.24700,5,25,41194,1524229119,0,dd0d4adc,4474077285">是发到未来</d><d p="407.45200,1,25,6684672,1524230939,0,f9244103,4474169642">英语不好还会这么多词</d><d p="987.13400,1,25,16777215,1524238924,0,10a0139f,4474611472">真由理的声音像不破爱花</d><d p="955.41400,1,25,16777215,1524239361,0,35ca32f7,4474634696">18/4/20</d><d p="777.03800,5,25,16707842,1524244263,0,db35daa0,4474839447">偷税</d><d p="1068.58800,1,25,16777215,1524246366,0,393f748e,4474894803">应该是只能到未来，不能到过去吧</d><d p="779.17600,1,25,16777215,1524267379,0,3e99d3ba,4475113496">影子胸好平</d><d p="972.45200,1,25,16777215,1524270590,0,38d21152,4475174894">现在是2088年</d><d p="1044.45900,5,25,16777215,1524271980,0,95eb4094,4475208932">瞬间就是永恒？</d><d p="1332.38900,1,25,16777215,1524273826,0,87cf4aed,4475264009">好僵硬啊</d><d p="1223.33200,1,25,16777215,1524275883,0,508701c2,4475328338">借了会怎样呢 突然好奇世界线会怎么变化</d><d p="1241.61900,1,25,16777215,1524275901,0,508701c2,4475328964">gg</d><d p="1271.41400,1,25,16777215,1524275931,0,508701c2,4475329916">海量gg</d><d p="1297.60300,1,25,16777215,1524275957,0,508701c2,4475330764">SF把他当成FB了</d><d p="1300.07300,1,25,16777215,1524275992,0,508701c2,4475331907">如果带入γ线的剧情，那么闪光指压师说的也很接近呢</d><d p="1330.99000,1,25,16777215,1524276024,0,508701c2,4475333195">万劫不复</d><d p="255.44500,1,25,16777215,1524276682,0,c3593b72,4475360465">我还想猜到这俩人的关系了，终结者吗？</d><d p="1324.11500,1,25,16777215,1524276995,0,5a7a995a,4475372450">zerozero狗蛋</d><d p="4.86200,1,25,16777215,1524280843,0,ba22e1aa,4475529451">蝴蝶效应？量子纠缠？</d><d p="859.19100,1,25,16777215,1524284535,0,56baf5a2,4475688331">药丸</d><d p="10.28200,1,25,16777215,1524285288,0,b5b3c1cc,4475725089">嘟嘟鲁</d><d p="13.74200,1,25,15138834,1524285309,0,b5b3c1cc,4475726108">嘟嘟噜</d><d p="305.51300,1,25,16777215,1524291099,0,a611dd19,4476017885">桌子在哪呢</d><d p="384.46700,1,25,16777215,1524291193,0,a611dd19,4476022047">乡愁是一桩矮矮的坟墓~~~</d><d p="258.19600,5,25,16777215,1524291375,0,b0ad0239,4476030155">真由理消失了?！</d><d p="248.05700,1,25,16777215,1524291645,0,bd8a8501,4476041794">别瞅了，这是你婶</d><d p="1010.91100,1,25,16777215,1524292433,0,bd8a8501,4476100767">不应该直接扯碎吗</d><d p="294.42000,1,25,16777215,1524296593,0,46257c39,4476281926">EX咖喱棒</d><d p="255.14400,1,25,15138834,1524297216,0,f7710a24,4476308096">瞅什么瞅</d><d p="6.02200,1,25,16707842,1524297761,0,1b9701c4,4476330591">请屏蔽关键词，高能</d><d p="1.05800,1,25,16707842,1524297799,0,1b9701c4,4476332117">请屏蔽关键词：高能</d><d p="950.77600,1,25,41194,1524298858,0,1b9701c4,4476437714">刚出生？！</d><d p="532.66600,1,25,16777215,1524299876,0,4196948e,4476481764">花泽土豆</d><d p="1145.68200,1,25,38979,1524304831,0,b6ccd27a,4476724949">说没有  说没有  说没有，千万别让他进来</d><d p="1153.56200,1,25,38979,1524304844,0,b6ccd27a,4476725602">完了</d><d p="1172.00200,1,25,38979,1524304887,0,b6ccd27a,4476727767">这妹子后期黑了，店长也黑了</d><d p="1219.20200,1,25,38979,1524304960,0,b6ccd27a,4476731551">唉，完了</d><d p="1268.84200,1,25,38979,1524305017,0,b6ccd27a,4476734396">完蛋</d><d p="1277.51600,1,25,16777215,1524307544,0,cfe09fff,4476863162">灭口吧</d><d p="22.41600,1,25,16777215,1524307809,0,fb6430ef,4476876348">？？？</d><d p="559.02600,1,25,16777215,1524310152,0,9d6c5a3f,4476996103">这双连吐槽，6的不行啊</d><d p="776.47000,1,25,16777215,1524310426,0,9d6c5a3f,4477010155">哈哈哈，金闪闪还是没逃过这个梗啊，愉悦</d><d p="1339.80900,1,25,16777215,1524314662,0,530be66d,4477231117">zero zero 狗蛋</d><d p="224.31700,5,25,15138834,1524315155,0,8519d22b,4477258164">嘟嘟噜</d><d p="1327.71800,5,25,15138834,1524316387,0,8519d22b,4477324415">前方高能</d><d p="568.12900,5,25,15138834,1524317445,0,40bed5b6,4477382477">4个辉光管，可以买影装了</d><d p="500.33200,5,25,16777215,1524318763,0,c378e67c,4477458297">花泽泡菜</d><d p="766.12800,1,25,16777215,1524321344,0,ffdad497,4477616950">桶子爆炸吧</d><d p="504.79000,5,25,14811775,1524321911,0,a92a3fd3,4477650770">花泽香肠</d><d p="1006.56900,1,25,16777215,1524323538,0,bc0c705d,4477747207">糟糕，喔精精没有了</d><d p="1277.11000,1,25,16777215,1524324903,0,62c5875a,4477827337">葫芦娃救爷爷</d><d p="982.57600,1,25,16777215,1524325117,0,fa29b6b4,4477839863">嘟嘟噜</d><d p="1305.30900,1,25,16777215,1524331196,0,73a1aa81,4478118487">F-布朗就是房东</d><d p="1057.39000,1,25,15138834,1524354679,0,e021d85a,4478402819">这是他能够跨越世界线的既视感</d><d p="1194.31800,1,25,16777215,1524370242,0,84d4e5ee,4478970434">你想要我的那个吗？想要就好好说出来，不说出来我就结束喽</d><d p="296.71600,1,25,16777215,1524372712,0,5e4002e2,4479097324">这是在难为我阿尔托莉雅(误)</d><d p="901.28600,5,25,16777215,1524373972,0,66fd2786,4479165952">感谢野生字幕君</d><d p="1265.43900,1,25,16777215,1524375501,0,409e3873,4479245694">GG</d><d p="303.19800,1,25,16776960,1524375684,0,6ee535ad,4479254997">梅林：好像有学生逃课</d><d p="669.88100,1,25,16777215,1524376090,0,974d7646,4479275237">切克切克骚</d><d p="256.73000,1,25,16777215,1524379443,0,cf2f1c21,4479434377">对眼了！</d><d p="510.68200,1,25,16777215,1524379811,0,d18b4660,4479451129">花泽卤菜</d><d p="1312.61200,1,25,16777215,1524388491,0,6ebf1937,4479834033">犯病</d><d p="355.08100,5,25,15138834,1524389206,0,c98eb872,4479864774">吾王剑锋所指，吾等心之所向</d><d p="216.12100,5,25,14811775,1524389498,0,cdec558c,4479877180">23333</d><d p="1078.18400,1,25,16777215,1524391940,0,db975b83,4479980889">2018</d><d p="177.58800,5,25,16777215,1524397731,0,1c0a416f,4480230815">vivoY79无压力</d><d p="296.40300,1,25,16707842,1524399201,0,870eba2a,4480295677">吾王赛高</d><d p="570.36700,5,25,15138834,1524399335,0,9659cf82,4480301449">看了3遍才注意到这4个布朗管</d><d p="270.25100,1,25,16777215,1524400723,0,b19ed18f,4480364512">唔姆</d><d p="298.10100,5,25,16777215,1524400780,0,1eabad96,4480367124">你是我的darling吗</d><d p="473.15200,1,25,16777215,1524403767,0,8a42a694,4480510083">胸针是个学霸吧，知道这么多英文和典故</d><d p="1195.06800,1,25,16777215,1524405217,0,8a42a694,4480582726">不可以</d><d p="1209.28000,1,25,16777215,1524405231,0,8a42a694,4480583449">不能借</d><d p="1223.21800,1,25,16777215,1524405252,0,8a42a694,4480584498">哎，没有大局观</d><d p="1223.21800,1,25,16777215,1524405257,0,8a42a694,4480584768">不谨慎</d><d p="294.36200,1,25,16777215,1524416498,0,78e49bcf,4481091949">小白！！！吾王！！！</d><d p="148.71900,1,25,16777215,1524417457,0,1e1f49f8,4481115228">为什么，小米2表示毫无压力(유∀유|||)</d><d p="5.64400,1,25,15138834,1524444308,0,fd920b87,4481350092">全程高能</d><d p="335.55800,1,25,8700107,1524447089,0,76667316,4481387512">那银子我的</d><d p="1140.00000,1,25,16777215,1524460344,0,92587198,4481703403">大脑在颤抖</d><d p="1322.70600,1,25,16777215,1524473005,0,46048a1d,4482000033">光头才是fb</d><d p="1312.90000,1,25,16777215,1524488577,0,e3488dcd,4482569664">放屁</d><d p="900.03200,1,25,16777215,1524492697,0,9f1c1a6,4482772664">感谢科普君</d><d p="1322.47200,1,25,16777215,1524494012,0,a5d74719,4482840554">放屁</d><d p="385.45900,1,25,16777215,1524496833,0,f9e0a394,4482987937">2333333</d><d p="506.47300,1,25,14811775,1524499176,0,750ddaf2,4483094137">不许你们侮辱我香菜姐姐(*｀･з･)ﾑｯ</d><d p="307.90200,1,25,16777215,1524503942,0,19fa91ad,4483266205">亚瑟是一个肉</d><d p="172.54300,1,25,15138834,1524503984,0,2673839f,4483267069">打工战士</d><d p="619.52500,1,25,16777215,1524536949,0,aae03692,4483567743">语法不行啊，小姐</d><d p="774.38100,1,25,16777215,1524537065,0,aae03692,4483569722">女儿，参见粑粑</d><d p="1043.79100,1,25,16777215,1524545494,0,14e7120f,4483780348">，。。</d><d p="638.63600,5,25,16777215,1524548004,0,24f6c524,4483867510">冈部有空气刘海</d><d p="861.41100,1,25,16777215,1524548769,0,9a34bcb0,4483888039">憋不住了哈哈哈哈哈</d><d p="490.02100,1,25,16777215,1524558819,0,88c0bc0b,4484142136">我算是发现了，全程就只有胖子在干活其余都在闲聊</d><d p="1358.91300,1,25,16777215,1524559002,0,fdea53d9,4484146696">开始跳线了</d><d p="551.32800,5,25,16750848,1524561653,0,d14eb910,4484209988">橘里橘气</d><d p="777.63400,5,25,16750848,1524561891,0,d14eb910,4484216000">偷税</d><d p="300.11400,1,25,16777215,1524564220,0,641b8a1a,4484284940">。。。</d><d p="765.79500,1,25,16777215,1524564745,0,641b8a1a,4484302745">王伸手是对你的恩赐啊八嘎</d><d p="910.24900,1,25,16777215,1524564869,0,7c5f87b5,4484307009">也就是说能发送给五天前的人，对方若有行动，时间线改写</d><d p="267.30700,5,25,16777215,1524567823,0,f9a95f7b,4484413763">我看你们就是刁难我阿尔托莉雅</d><d p="1278.28900,1,25,16777215,1524577164,0,380464c9,4484800351">这一切都是命运石之门的选择</d><d p="225.00200,1,25,16777215,1524577654,0,2b5931f5,4484823151">嘟嘟噜~~~~</d><d p="3.08300,1,25,16777215,1524577674,0,4f60a1a1,4484823996">现在开始链接月读空间</d><d p="902.38200,1,25,16777215,1524578357,0,2b5931f5,4484855725">感谢野生字幕君</d><d p="1260.72300,1,25,16777215,1524578813,0,2b5931f5,4484877356">嘟嘟噜</d><d p="1267.66200,1,25,16777215,1524578826,0,2b5931f5,4484877981">嘟嘟噜</d><d p="985.04400,1,25,16777215,1524585076,0,3b31a4df,4485183080">GATE OF STEINER</d><d p="1025.11000,1,25,15138834,1524585227,0,3b31a4df,4485189229">α线里的助手和β线里的冈伦。。。</d><d p="1321.81100,1,25,15138834,1524585660,0,3b31a4df,4485206284">高虐即将开始。。。</d><d p="162.05600,1,25,16777215,1524633012,0,ed371e0,4485872248">游戏里面没有这家店！！！</d><d p="533.27400,5,25,6830715,1524633624,0,da133865,4485892845">花泽芭娜娜</d><d p="1366.79000,1,25,16777215,1524635804,0,c083229,4485950347">前面的，你想笑就笑吧</d><d p="212.82200,1,25,16777215,1524639550,0,ee0fa42,4486027853">23333</d><d p="550.85100,1,25,16777215,1524643169,0,f7f2b00e,4486094512">糟糕的台词</d><d p="275.35500,1,25,16777215,1524643951,0,9fdb0643,4486110075">矮脚桌</d><d p="504.75200,1,25,16777215,1524653669,0,6752e729,4486387695">花泽韭菜</d><d p="101.33900,1,25,16777215,1524663892,0,a1a57aa9,4486851093">红米5plus毫无压力</d><d p="776.92100,1,25,16777215,1524672896,0,8db08746,4487257814">偷悦</d><d p="219.46400,1,25,16777215,1524709902,0,b441e359,4487654158">233333</d><d p="550.22200,1,25,15138834,1524710665,0,a189f889,4487667002">花泽很菜</d><d p="1290.23300,1,25,16777215,1524719650,0,428e34ef,4487899832">你倒是灭口啊啊啊</d><d p="379.73200,5,25,15138834,1524719986,0,f9e34801,4487911358">月山习？？</d><d p="393.72100,1,25,16777215,1524724057,0,54e469cd,4488052966">over dive，OD</d><d p="530.42100,5,25,16777215,1524738115,0,f7406463,4488414785">花泽藠头</d><d p="530.42100,5,25,16777215,1524738125,0,f7406463,4488415162">花泽大蒜</d><d p="1277.68900,1,25,16777215,1524739247,0,90ce2e96,4488454727">求你灭口</d><d p="770.19900,5,25,16707842,1524740191,0,a189f889,4488489138">Jesus</d><d p="302.63500,1,25,16777215,1524740702,0,4843b571,4488509519">吾王剑锋所指，吾等心之所向</d><d p="552.00300,1,18,41194,1524743915,0,4777a561,4488633610">百合力场</d><d p="305.83500,1,25,16777215,1524744145,0,4afe25e4,4488642533">饭桌会议哦怕是</d><d p="516.01300,1,25,16777215,1524744473,0,d21ef57c,4488655028">花泽扣肉</d><d p="1316.50200,1,25,16777215,1524745376,0,d21ef57c,4488691709">副本</d><d p="168.21200,1,25,16777215,1524747234,0,cbad7590,4488768010">米6无压力</d><d p="292.05200,1,25,16777215,1524749437,0,3e45e9d7,4488861413">哈哈</d><d p="298.63300,1,25,16777215,1524749456,0,3e45e9d7,4488862260">吾王</d><d p="761.82900,1,25,16777215,1524750566,0,3863b86b,4488912390">心疼</d><d p="1078.69100,1,25,16777215,1524750608,0,cbad7590,4488914205">2018</d><d p="80.72000,1,25,16777215,1524779850,0,f23309b7,4489571495">这是反派一号</d><d p="1348.67800,1,25,16777215,1524782012,0,f23309b7,4489584446">因为桐生就是那个组织的成员</d><d p="42.02100,5,25,15138834,1524814575,0,4f38f660,4490351004">坏女人</d><d p="91.81800,1,25,16777215,1524821029,0,a95de4c2,4490554750">高清无压力</d><d p="100.18100,1,25,16777215,1524821046,0,a95de4c2,4490555265">高清无压力</d><d p="853.37100,1,25,16777215,1524824470,0,6365aee3,4490674783">23333</d><d p="1062.14500,1,25,16777215,1524835842,0,2b04e97b,4491176218">。。</d><d p="741.10200,1,25,16777215,1524847811,0,be2699c8,4491710617">啫喱人有個矛盾！爲啥骨頭和眼睛沒有變</d><d p="568.53400,5,25,15138834,1524849936,0,68365053,4491761315">前方高能</d><d p="381.87300,1,25,16777215,1524874290,0,ae26943f,4491967935">好腿</d><d p="1040.26700,5,25,15138834,1524882136,0,249b8a26,4492093646">回头亦是地狱</d><d p="1070.69700,5,25,15138834,1524882203,0,249b8a26,4492095048">回头亦是绝路</d><d p="536.94100,1,25,16777215,1524883496,0,53e58d05,4492121179">助手听得懂。。这意味着2333</d><d p="505.78400,5,25,16707842,1524890012,0,6a1a6819,4492309785">花泽类</d><d p="328.10000,1,25,16777215,1524902487,0,e014158a,4492854578">K中的红之王周防尊</d><d p="236.23300,1,25,16777215,1524908177,0,7415e493,4493019373">嘟嘟噜</d><d p="507.24900,1,25,16777215,1524912269,0,1c8b7098,4493179831">花泽咸菜</d><d p="521.28900,1,25,16777215,1524912301,0,1c8b7098,4493181192">花泽白菜</d><d p="707.22100,5,25,16777215,1524915572,0,1b34dd3e,4493323611">左声道</d><d p="172.57300,1,25,16777215,1524920158,0,e4146b93,4493546381">我的最爱呀</d><d p="392.70800,1,25,16777215,1524920386,0,e4146b93,4493557950">乡愁？</d><d p="169.85400,1,25,16777215,1524920842,0,fb52da0e,4493581512">电脑表示毫无压力</d><d p="233.18900,1,25,16777215,1524924788,0,1c6b02b7,4493791996">嘟嘟噜</d><d p="650.76500,1,25,16777215,1524927144,0,b590a9d5,4493924376">为啥男主座时光机没变绿啊。。。</d><d p="31.90400,1,25,16777215,1524930841,0,418d0bf8,4494123923">稳住 我们能懂</d><d p="246.93500,1,25,16777215,1524931040,0,a57d3070,4494133981">衣服看的好难受啊</d><d p="162.33100,5,25,3355443,1524935029,0,4a33bb23,4494296891">瑟瑟发抖</d><d p="414.43800,1,25,16777215,1524937417,0,fbb17c15,4494368033">桶哥是个明白人</d><d p="846.63400,1,25,16777215,1524951945,0,483257dd,4494533235">时光机是宅男做出来的。。</d><d p="6.10100,1,25,16777215,1524962411,0,31c4612b,4494689206">eddd</d><d p="295.28200,1,25,16777215,1524981997,0,86c07209,4495479875">这个番很有意思啊</d><d p="257.69700,1,25,16777215,1524982250,0,6f425482,4495490869">消失的真由氏</d><d p="282.22200,1,25,16777215,1524992868,0,7c7b5bd0,4495943516">记录的地平线+10086</d><d p="467.29900,1,25,16777215,1524993069,0,7c7b5bd0,4495952690">D-sword</d><d p="1174.44200,1,25,16777215,1524997239,0,30f974b8,4496154208">开始了 怀表</d><d p="395.56600,1,25,16777215,1524998943,0,2455172b,4496240699">GN-DRIVE？</d><d p="76.14100,1,25,15138834,1525001709,0,e15e5ce7,4496383725">op很好听</d><d p="152.36100,1,25,15138834,1525001793,0,e15e5ce7,4496387951">孤独的观测者</d><d p="485.79900,1,25,15138834,1525002153,0,e15e5ce7,4496406945">助手吐槽傲娇还可爱</d><d p="517.19800,1,25,15138834,1525002204,0,e15e5ce7,4496409696">牧濑蓝莉栖</d><d p="522.81800,1,25,15138834,1525002221,0,e15e5ce7,4496410619">牧濑蓝莉栖</d><d p="551.55900,1,25,15138834,1525002255,0,e15e5ce7,4496412466">百合大法好</d><d p="557.67900,1,25,15138834,1525002269,0,e15e5ce7,4496413223">百合力场</d><d p="832.85500,1,25,15138834,1525002557,0,e15e5ce7,4496428504">这个笑好可爱啊</d><d p="904.65600,1,25,15138834,1525002635,0,e15e5ce7,4496432660">感谢字幕君</d><d p="1309.07500,5,25,14811775,1525002650,0,3b362fc0,4496433502">副本</d><d p="964.75600,1,25,15138834,1525002704,0,e15e5ce7,4496436321">此刻应有掌声</d><d p="1273.56300,1,25,15138834,1525003077,0,e15e5ce7,4496455727">这她们怎么会事先知道，还说开猪队友了？？</d><d p="508.63800,1,25,16777215,1525004510,0,ca900698,4496532799">就是你们，香菜现在都不笑了</d><d p="768.14200,1,25,16777215,1525004781,0,ca900698,4496547341">肥宅有错么！</d><d p="229.99800,1,25,16777215,1525004810,0,60e97713,4496548929">前面驼鹿行动的那个，应该是嘟嘟～嘟嘟嘟～嘟～驼鹿行动</d><d p="1023.47400,1,25,16777215,1525006437,0,9c3f971a,4496637487">接受时之螶的爱吧！！！</d><d p="1333.48100,1,25,52479,1525007960,0,77e5f1c0,4496722466">我再次确认了，这是个搞笑番</d><d p="402.32500,1,25,16777215,1525008876,0,38d96067,4496775303">。。。</d><d p="383.93500,1,25,16777215,1525010915,0,95a19076,4496897307">233333333</d><d p="524.01600,1,25,16777215,1525011055,0,95a19076,4496905656">23333333</d><d p="1274.85700,1,25,16777215,1525013468,0,b1587e32,4497055919">操作</d><d p="526.63000,1,25,16777215,1525015676,0,b5c20a2,4497185665">建议屏蔽关键词 花泽</d><d p="479.61300,5,25,16707842,1525023384,0,2bedc110,4497523792">奇美拉那个，我看见了</d><d p="381.47500,1,25,16777215,1525025418,0,7f395bab,4497574279">hhh</d><d p="553.56200,1,25,16777215,1525030978,0,7c3f5381,4497658211">疯狂快进中二剧情</d><d p="304.09800,1,25,16777215,1525041900,0,98a21b34,4497739417">吾王美如画</d><d p="42.90100,1,25,16777215,1525047547,0,2ed2d3d0,4497832680">&lt;(￣3￣)&gt;哼！</d><d p="522.76500,5,25,15138834,1525049835,0,e517418f,4497895239">泥门垢了。</d><d p="206.90100,1,25,16777215,1525054221,0,2a29e4f7,4498054418">成本全花在风扇上。。。</d><d p="21.08100,1,25,16777215,1525056445,0,d5a0edcd,4498148847">为什么不取下来</d><d p="34.03700,1,25,16777215,1525056841,0,784a4db2,4498166740">稳住了</d><d p="515.48000,1,25,16777215,1525059782,0,149cfa9d,4498315135">绝了</d><d p="517.77400,1,25,15138834,1525059791,0,149cfa9d,4498315616">绝了</d><d p="894.93600,1,25,16777215,1525060285,0,4d47a9df,4498338865">钙不是Ca吗 Cao是个啥</d><d p="1024.70200,5,25,15138834,1525062455,0,8e4f1a9d,4498446400">出现了，不可视界限！</d><d p="253.69500,1,25,16777215,1525063484,0,ba4f1c1d,4498501725">……</d><d p="171.92400,1,25,16777215,1525064067,0,854e1ecb,4498533257">吉野家</d><d p="949.48600,1,25,16777215,1525064223,0,ba4f1c1d,4498541742">可惜不是我这条世界线</d><d p="1266.62800,1,25,16777215,1525064551,0,ba4f1c1d,4498559649">GG GG GG</d><d p="1349.03900,1,25,16777215,1525064671,0,ba4f1c1d,4498565979">说困了的，很有趣啊</d><d p="741.95400,5,25,16707842,1525065598,0,de680982,4498617954">好腿</d><d p="16.29700,1,25,16777215,1525065967,0,58b1eb4c,4498637535">五天了你们都不想办法把它弄走吗</d><d p="972.14600,5,25,15138834,1525066632,0,51f70e01,4498672546">陈独秀已经坐下了</d><d p="422.22600,1,25,16777215,1525066959,0,fa08c872,4498689711">时间溯行者</d><d p="1286.60900,1,25,65535,1525070704,0,eb829fec,4498876160">现在灭口啊</d><d p="967.66600,1,25,16777215,1525080463,0,a7a70ab8,4499353787">陈独秀同志你的痔疮又犯了吗</d><d p="266.08600,1,25,16777215,1525085885,0,bb88dc4,4499647615">真的不见了！！！</d><d p="511.89100,1,25,15138834,1525086264,0,db7b41c4,4499668359">完结撒花泽香菜</d><d p="1351.55900,1,25,16777215,1525090829,0,66ba2b91,4499931925">开头打工妹收到的邮件似乎就是re FB</d><d p="1339.61200,1,25,16777215,1525090918,0,1c9e63f5,4499937539">这一切都是命运石之门选择</d><d p="434.84600,1,25,16777215,1525091541,0,732e4cf5,4499975507">溯游从之</d><d p="1323.29000,1,25,16777215,1525091955,0,28a3075d,4500001103">你们被005号队友给团灭了</d><d p="278.94600,1,25,16777215,1525094080,0,1a65b9d9,4500134173">崔悲伤</d><d p="1190.00900,1,25,15138834,1525096306,0,b92901f3,4500284172">主角凉了</d><d p="1198.51800,1,25,15138834,1525096328,0,b92901f3,4500285636">她是sern的人</d><d p="699.92700,1,25,38979,1525096558,0,75b640c4,4500300873">我为什么大半夜看这个</d><d p="1187.16700,1,25,16777215,1525097339,0,a7b0032a,4500353857">小田同学是猪小田同学是猪(￣(●●)￣)</d><d p="960.28300,1,25,16777215,1525097366,0,a7b0032a,4500355693">小田同学是猪</d><d p="1060.87800,1,25,16777215,1525097389,0,a7b0032a,4500357169">小田同学是猪(￣(●●)￣)</d><d p="1071.12200,1,25,16777215,1525097399,0,a7b0032a,4500357852">小田同学是猪</d><d p="1080.36100,1,25,16777215,1525097410,0,a7b0032a,4500358619">小田同学是猪</d><d p="1089.37300,1,25,16777215,1525097419,0,a7b0032a,4500359249">小田同学是猪</d><d p="384.93800,5,25,16777215,1525098926,0,68ae4e85,4500460142">你们是怎么忍受中二病的</d><d p="633.08400,5,25,16777215,1525099258,0,68ae4e85,4500482269">aerhead 空头  airdrop 猪头</d><d p="182.54700,5,25,16777215,1525100365,0,e849349,4500555797">苹果xxx表示无压力</d><d p="983.47800,1,25,16777215,1525100947,0,b09b90ea,4500593746">真有理是天使啊(`3`)</d><d p="1300.13300,5,25,16707842,1525101520,0,7ca03824,4500631172">Facebook？</d><d p="42.66200,1,25,16777215,1525114930,0,2f3e2692,4501151770">fb</d><d p="45.38100,1,25,16777215,1525114955,0,2f3e2692,4501152176">是布朗大叔，他是机关的人</d><d p="553.03000,1,25,15772458,1525114964,0,50b4d0a9,4501152322">橘势大好</d><d p="1081.71700,1,25,16777215,1525132449,0,e4a79226,4501328620">今天不是18/5/1劳动节吗</d><d p="239.43200,1,25,16777215,1525132718,0,bd17644,4501334322">冈轮，轮肛</d><d p="1273.77700,1,25,14811775,1525133758,0,50b4d0a9,4501358864">百合大法。</d><d p="232.48800,1,25,14811775,1525133917,0,48b26d88,4501362972">嘟嘟噜</d><d p="491.92500,1,25,16777215,1525138471,0,1c9a96c3,4501516609">假说演绎吗？</d><d p="214.44700,1,25,16777215,1525145492,0,8ef053b7,4501863472">这个梗用烂了</d><d p="1322.10700,1,25,16777215,1525146584,0,8ef053b7,4501921367">随便拉人</d><d p="468.00000,1,25,16777215,1525148148,0,6c4a8ffc,4502006600">嘟嘟噜</d><d p="900.96300,1,25,16777215,1525149533,0,919c248a,4502083362">缺钙会导致脾气暴躁</d><d p="1203.32200,1,25,16777215,1525151777,0,b97f608c,4502214581">凉凉</d><d p="1028.56800,1,25,16777215,1525154524,0,473e239,4502370214">蛤？</d><d p="1246.51800,1,25,16777215,1525157227,0,af80f571,4502511233">我看你们药丸</d><d p="1267.27900,1,25,16776960,1525157374,0,af80f571,4502518958">凉凉</d><d p="1286.20100,1,25,16777215,1525159866,0,1c4a52fc,4502642937">看了一下午，就想说两个字，拖沓！</d><d p="297.30500,5,25,15138834,1525161256,0,dc198404,4502710948">参见吾王</d><d p="901.79100,5,25,38979,1525161629,0,f1cb457e,4502729498">感谢野生字幕君</d><d p="413.39100,5,25,15138834,1525162833,0,dc198404,4502788806">官方吐槽</d><d p="530.15700,1,25,16777215,1525167784,0,4b02a392,4503036757">不是变态，是变态绅士</d><d p="324.64900,1,25,16777215,1525169523,0,29462353,4503122070">  小天使</d><d p="1267.12300,1,25,16777215,1525169792,0,e1d26f7f,4503135412">哈哈哈哈</d><d p="297.85700,1,25,16777215,1525172197,0,cf29aca2,4503255568">亚瑟王怎么可能是女孩!!!!</d><d p="382.18700,1,25,16777215,1525174493,0,f1c2e153,4503367418">多啦爱梦</d><d p="31.53900,1,25,16777215,1525176285,0,2291e7bc,4503456398">好，稳住</d><d p="461.03700,1,25,16777215,1525176459,0,2b9b5efd,4503465781">嘟嘟噜</d><d p="295.99800,1,25,16707842,1525179221,0,e52b2506,4503610325">吾王剑锋所指，吾等心之所向</d><d p="526.93400,1,25,16777215,1525181929,0,d063f127,4503760191">花泽白菜</d><d p="79.57900,1,25,16777215,1525183238,0,ead29be8,4503839158">163是哪里的价格……steam原价100逢打折50……</d><d p="247.26300,1,25,16777215,1525183946,0,e7de1246,4503879579">嘟嘟噜</d><d p="728.03300,1,25,16777215,1525183958,0,4c8ffef2,4503880286">这人是不是从未来过来的啊</d><d p="444.67700,5,25,16777215,1525184160,0,e7de1246,4503892070">嘟嘟噜</d><d p="522.48000,5,25,16777215,1525184253,0,e7de1246,4503897462">花泽酸菜</d><d p="1321.44900,1,25,15138834,1525184722,0,63d9048e,4503924771">引狼入室啊</d><d p="1264.32600,5,25,16777215,1525185123,0,e7de1246,4503948166">嘟嘟噜</d><d p="302.08100,1,25,16777215,1525185553,0,58f3d4fc,4503973007">亚瑟·潘德拉贡</d><d p="380.96600,5,25,15138834,1525189229,0,bf27750c,4504175179">TRANS-AM!</d><d p="80.60000,1,25,16777215,1525189455,0,61f3af5f,4504186446">好像女主</d><d p="227.88000,1,25,16777215,1525190517,0,ebdd17cd,4504237104">嘟嘟噜</d><d p="592.97900,1,25,16777215,1525198956,0,a592dac5,4504463922">为什么？这不科学啊！</d><d p="297.52300,1,25,16777215,1525235049,0,61066678,4504906112">圆桌13骑士在此参上</d><d p="1274.79100,1,25,16777215,1525237876,0,6908ec13,4505020663">233</d><d p="697.46100,5,25,16777215,1525249265,0,c720db37,4505294645">话说为啥是绿色？</d><d p="1261.58700,1,25,15138834,1525257345,0,f875eb4c,4505534216">嘟嘟噜</d><d p="1324.27500,1,25,16777215,1525260089,0,e1376d93,4505646111">传销组织</d><d p="763.75200,1,25,38979,1525261220,0,db8fc42d,4505693553">这TM不是说我么</d><d p="168.41400,1,25,16777215,1525263609,0,110c5b67,4505797350">骁龙821</d><d p="1298.38100,5,25,15138834,1525271136,0,912eae25,4506156612">First Blood </d><d p="50.16000,1,25,15138834,1525307819,0,5055eb2,4506809239">这都是命运石之门的选择</d><d p="945.15100,5,25,15138834,1525313095,0,3c237f77,4506884188">変態。</d><d p="1321.05900,1,25,16777215,1525320552,0,ec7aef12,4507033675">mdzz。。。</d><d p="1004.48600,1,25,16777215,1525323898,0,bd684ca6,4507158933">重重叠加</d><d p="526.26700,5,25,16707842,1525325250,0,ce99bf88,4507207439">不能放别的吗。。。。</d><d p="719.40200,1,25,16777215,1525326965,0,4ab0d6a2,4507256856">万恶之源</d><d p="214.38200,1,25,16777215,1525336691,0,f0634b4b,4507459317">打工少女就是提托，桶是她爸爸</d><d p="254.31700,1,25,16777215,1525336781,0,f0634b4b,4507461393">为什么仇视女主是因为在原来的世界线女主研发时间机器帮助机关统治了世界</d><d p="1276.25500,1,25,16777215,1525336840,0,f0634b4b,4507462754">这个女人发的邮件是让fb赶紧取回ibn</d><d p="1264.52100,1,25,16777215,1525341207,0,6eaa3179,4507696823">gg</d><d p="1270.52600,1,25,16777215,1525341213,0,6eaa3179,4507697035">23333</d><d p="190.01800,1,25,16777215,1525347167,0,9ea969b,4507918799">催泪番？</d><d p="616.63300,1,25,16777215,1525348013,0,e6fa34c4,4507954142">为什么是was，而不是is</d><d p="103.72200,1,25,16777215,1525348174,0,a80cb6a,4507960688">超清无压力</d><d p="1325.09800,1,25,16777215,1525351143,0,7e7ce78a,4508086086">有什么样的队员就有什么样的队长 真理啊！</d><d p="1270.14700,1,25,16777215,1525354926,0,1a538d13,4508258154">男主生无可恋啊</d><d p="623.72700,1,25,16777215,1525355574,0,2b6372d8,4508290301">为什么是过去式？</d><d p="1152.39400,1,25,16777215,1525356159,0,2b6372d8,4508319111">为什么他会知道男主有ibn？</d><d p="254.41700,1,25,16777215,1525360957,0,8e543664,4508566250">确认过眼神</d><d p="388.53300,1,25,16777215,1525361112,0,8e543664,4508573676">233333</d><d p="652.69400,1,25,16777215,1525361389,0,8e543664,4508587244">2333333</d><d p="760.81600,1,25,16777215,1525361501,0,8e543664,4508592688">2333333</d><d p="806.65600,1,25,16777215,1525361561,0,8e543664,4508595636">233333</d><d p="221.83600,1,25,16777215,1525363141,0,75e6ff6d,4508666486">嘟嘟噜</d><d p="261.19200,1,25,16777215,1525363228,0,75e6ff6d,4508670014">嘟嘟噜不见了？</d><d p="444.67700,1,25,16777215,1525363427,0,75e6ff6d,4508677953">嘟嘟噜</d><d p="675.21900,1,25,16777215,1525363694,0,75e6ff6d,4508688216">真的骚2333333</d><d p="757.95400,1,25,16777215,1525363780,0,75e6ff6d,4508691372">233333333</d><d p="938.80500,1,25,16707842,1525364017,0,75e6ff6d,4508700508">hentai</d><d p="1259.24600,1,25,16777215,1525364368,0,75e6ff6d,4508713415">嘟嘟噜</d><d p="1272.29100,1,25,16777215,1525364385,0,75e6ff6d,4508714031">gg</d><d p="1298.82500,1,25,16777215,1525364426,0,75e6ff6d,4508715539">FBI？</d><d p="1420.06500,1,25,16777215,1525364503,0,75e6ff6d,4508718349">留一条</d><d p="726.34100,1,25,16777215,1525374933,0,1835c63e,4508906324">为什么你单手打字这么快啊</d><d p="510.89000,5,25,16777215,1525395636,0,a7b40159,4509069318">地上的电线</d><d p="517.71900,1,25,16777215,1525402344,0,b4d71571,4509187663">花泽芥菜</d><d p="1166.76500,1,25,16777215,1525409438,0,2b506795,4509408794">中二病看着太累了。。。</d><d p="1324.88900,1,25,16777215,1525410747,0,79183f31,4509468425">强行拉人入伙</d><d p="563.71100,5,25,16777215,1525411946,0,af9c1745,4509514370">Operation Chimera</d><d p="1019.19800,1,25,16777215,1525413188,0,dc7c5953,4509553933">事件视界？</d><d p="557.69500,1,25,16777215,1525413240,0,810c6169,4509555542"> 宁宁也这样过</d><d p="247.85600,1,25,16777215,1525425011,0,4200e0d1,4509878740">活着的助手</d><d p="712.17600,1,25,16777215,1525425491,0,4200e0d1,4509894136">命运石0的时候一直正经</d><d p="280.11200,1,25,16777215,1525426872,0,708718a4,4509941600">嘟嘟噜</d><d p="451.76000,1,25,16777215,1525427047,0,708718a4,4509947953">ddl</d><d p="453.27500,1,25,16777215,1525427054,0,708718a4,4509948233">嘟嘟噜</d><d p="275.66400,1,25,16777215,1525428397,0,f47f3253,4509999167">一拳一个嘟嘟怪</d><d p="684.94700,1,25,38979,1525430101,0,bc9694ad,4510073002">绿色。有毒。有毒。</d><d p="788.49700,1,25,16777215,1525433283,0,679fb79d,4510221739">偷税</d><d p="498.65600,1,25,16777215,1525433341,0,49312472,4510224402">BGM突变</d><d p="169.81300,1,25,16777215,1525434166,0,f658aeb6,4510263153">iPhoneX无压力</d><d p="173.01000,1,25,16777215,1525437673,0,8a01989,4510440791">肥牛饭————————</d><d p="447.25100,1,25,16777215,1525444742,0,a5d886ea,4510822899">嘟嘟噜</d><d p="712.60000,1,25,16777215,1525445033,0,a5d886ea,4510839881">你谁啊</d><d p="907.20300,1,25,16777215,1525445235,0,a5d886ea,4510851695">我白活了</d><d p="1329.05900,1,25,15138834,1525448750,0,37b92333,4511101115">这里男主认为她也在中二</d><d p="692.46500,1,25,16777215,1525449239,0,190ba2d9,4511128743">吓到我了。。</d><d p="608.35600,1,25,16777215,1525449704,0,d4ec3fce,4511154009">(ﾟ⊿ﾟ)ﾂ</d><d p="1335.86100,1,25,15138834,1525450206,0,c8b8d62c,4511180049">贼了贼了狗蛋</d><d p="687.37200,1,25,16777215,1525451972,0,6ca1b810,4511262115">吓尿了去擦你吗</d><d p="932.15700,1,25,16777215,1525452545,0,716d1901,4511291854">别秀了桶子</d><d p="931.01800,1,25,16777215,1525482953,0,ba86c1da,4511762253">太紧了吧</d><d p="755.30700,5,25,16711680,1525483511,0,cb0d9e3b,4511778332">肥宅到底做错了什么</d><d p="651.26200,1,25,16777215,1525489990,0,2cbd3c9b,4512016837">……</d><d p="380.19800,1,25,16777215,1525490346,0,6c8d29e8,4512031772">胸针太骚了</d><d p="533.84700,1,25,16777215,1525490566,0,6c8d29e8,4512040941">不是变态！！是ka ci la（桂）哒！！</d><d p="314.97700,1,25,16777215,1525500129,0,2f224608,4512508957">扫地僧</d><d p="312.54900,1,25,65280,1525501663,0,76d4e779,4512577180">吾王比水，绝代风流</d><d p="935.25800,1,25,16777215,1525505836,0,cb1364e4,4512755124">糟糕的台词</d><d p="1008.31500,1,25,16777215,1525506937,0,d61f55a5,4512801201">重重叠加</d><d p="1013.67500,1,25,16777215,1525507761,0,5159e8ce,4512835482">纳吉的宝洞</d><d p="472.23400,1,25,16777215,1525510791,0,dfc4ea41,4512970403">driver-smail</d><d p="1305.77100,1,25,16777215,1525512167,0,dfc4ea41,4513033693">fjrst blood哈哈哈哈</d><d p="269.62700,1,25,16707842,1525513698,0,93c6bb25,4513113025">十二个来自赛博坦的骑士.......</d><d p="296.22700,1,25,16707842,1525513858,0,93c6bb25,4513120925">霜之哀伤</d><d p="234.08400,5,25,3381759,1525514332,0,a8e7fe4c,4513144884">嘟嘟噜（1/1）</d><d p="1108.81100,1,25,16777215,1525515968,0,7b7b6d7,4513229069">我喜欢这个妹子。。啊好喜欢</d><d p="87.32500,1,25,16777215,1525517181,0,b2e331d3,4513293189">郭德纲的你走错了喂</d><d p="937.65800,1,25,16777215,1525517472,0,b5ecd5b9,4513308889">我们可以往后倒再听一边</d><d p="26.54100,1,25,16777215,1525518469,0,e5edaff2,4513362645">高能</d><d p="776.35700,5,25,16707842,1525518677,0,5dec2979,4513374126">偷税</d><d p="1046.52700,1,25,16777215,1525519442,0,e5edaff2,4513416434">不可视境界线</d><d p="1297.46100,1,25,9487136,1525522365,0,959fda41,4513586561">难道是FBI?</d><d p="597.54600,1,25,16777215,1525522753,0,6424d270,4513610301">没有控制变量</d><d p="468.55400,1,25,16776960,1525523480,0,b5fbfa25,4513653413">dick mail</d><d p="299.94900,1,25,16777215,1525524133,0,6abb5d90,4513692013">saber</d><d p="1263.26800,1,25,16777215,1525524561,0,aecf5d68,4513717857">嘟嘟噜</d><d p="239.47600,1,25,16777215,1525527001,0,2b2e0237,4513864351">嘟嘟噜</d><d p="77.32200,1,25,16777215,1525529280,0,2faa56ea,4514026831">比屋定真帆哪里去了</d><d p="241.43100,1,25,16777215,1525529374,0,2faa56ea,4514032565">玲羽是桶子的女儿吧，怎么那么不像呢</d><d p="1169.90100,1,25,15138834,1525532444,0,aeaf1d,4514226761">别单纯的说她是坏的，只能说α世界线她算敌对势力sern的人</d><d p="1171.94400,1,25,15138834,1525532496,0,aeaf1d,4514230115">β世界线萌郁帮过胸针的（0里）</d><d p="226.29400,5,25,15138834,1525533593,0,57620c87,4514299651">香菜的声音为什么这么好听</d><d p="733.93100,5,25,15138834,1525534172,0,57620c87,4514336129">脱衣女的怕不是炮姐看多了</d><d p="69.12100,1,25,16777215,1525536670,0,b68074f1,4514485741">原来是你放的屁</d><d p="158.99500,1,25,16777215,1525552298,0,36ed81a8,4514890062">注意时间</d><d p="1216.55900,1,25,16777215,1525553444,0,36ed81a8,4514897602">完了</d><d p="310.52900,1,25,16777215,1525571039,0,34314f7e,4515179571">圆桌会议:5费，随机召唤两个指挥官从者</d><d p="214.01400,1,25,16777215,1525572331,0,7c719c8c,4515230446"> 禁止携带瞩目</d><d p="385.98300,1,25,16777215,1525573575,0,b99093fe,4515284601">。。。。</d><d p="1031.89600,1,25,16777215,1525573701,0,7c719c8c,4515290096">太暴力了</d><d p="937.94700,1,25,16777215,1525574416,0,b4e7740a,4515321998">噗蛤蛤蛤蛤蛤蛤蛤蛤蛤</d><d p="141.87200,5,25,16777215,1525577572,0,7d7e0b9b,4515470804">在这儿停顿</d><d p="350.63700,1,25,0,1525578327,0,1b2c0a0e,4515507142">哈哈</d><d p="1028.03700,1,25,16777215,1525579721,0,7d7e0b9b,4515577371">哦，在这儿停顿！</d><d p="800.12500,5,25,15138834,1525585733,0,f666ea25,4515924536">注意打工战士的动作</d><d p="913.53600,1,25,16777215,1525589039,0,ce408849,4516096467">就是说1秒1个小时</d><d p="538.57900,1,25,16777215,1525590135,0,67b1c20f,4516150295">花泽托马斯勒布朗蒙奇-D-</d><d p="656.78600,1,25,16777215,1525591979,0,82537de,4516238680">fff</d><d p="510.40000,1,25,16777215,1525600070,0,5663a24c,4516626050">为神马没有去评论</d><d p="775.95700,1,25,16777215,1525601172,0,414d110a,4516678865">偷税</d><d p="11.58800,1,25,16777215,1525603498,0,9b809744,4516789267">哈哈</d><d p="98.23200,1,25,16777215,1525603584,0,9b809744,4516793351">BGM变了</d><d p="82.99700,1,25,16777215,1525613796,0,d4502ad2,4517309571">评分 9.8  应该很好看</d><d p="710.06400,1,25,16777215,1525613967,0,91cbecd7,4517318776">性感开叉裙</d><d p="1315.03500,1,25,16777215,1525614669,0,91cbecd7,4517356862">fuck b~</d><d p="175.44400,1,25,15138834,1525616578,0,eff241f6,4517465272">表示强行喝过鸡蛋汁</d><d p="640.87300,1,25,16777215,1525621026,0,2f0a1180,4517714076">还会是无意义的邮件，要是发来什么重要信息估计会改变世界线吧</d><d p="28.44000,1,25,16777215,1525626008,0,db83d19d,4517920321">这个不是卫星吧，是时间机器</d><d p="1103.62600,1,25,16777215,1525627455,0,1b6c2fca,4517959669">有部日本的恐怖片就是这样的！！</d><d p="1300.40600,1,25,16777215,1525644101,0,6a62b13a,4518121714">Facebook</d><d p="176.84200,1,25,16777215,1525680053,0,8f69f01e,4518846305">小米6表示毫无压力  </d><d p="379.74600,1,25,16777215,1525684958,0,caf199ba,4518964928">莫名高帧</d><d p="1075.38500,5,25,16777215,1525686959,0,f668f90c,4519028419">已经开始有时间了</d><d p="1157.80000,5,25,16777215,1525687076,0,f668f90c,4519032418">不行啊！别！</d><d p="1077.49300,1,25,16777215,1525688452,0,d0e39011,4519081958">你们怎么回事，我这都新纪7172年了</d><d p="1028.83000,1,25,16777215,1525689020,0,df991326,4519103793">靠近黑洞吗，事件穹界</d><d p="995.21300,5,25,15138834,1525689299,0,6dbc4d7a,4519114882">度集如季</d><d p="188.24600,5,25,16777215,1525691313,0,31d2d484,4519198897">这风扇帧数好高</d><d p="744.02300,1,25,16777215,1525700812,0,19b8a5f,4519635390">扫本模式启动</d><d p="123.09600,1,25,16777215,1525702853,0,57b3a173,4519747730">为什么骁龙625表示无压力</d><d p="223.45700,1,25,16777215,1525702958,0,57b3a173,4519753560">嘟嘟噜</d><d p="1388.33100,1,25,16777215,1525710310,0,cc06a27,4520151288">突然想到，这女的年龄表现，，是不是打工妹</d><d p="1268.84200,1,25,16777215,1525710520,0,23466232,4520158531">233</d><d p="1311.26200,1,25,16777215,1525710566,0,23466232,4520160069">233</d><d p="1272.85400,1,25,16777215,1525713238,0,14fd9f1e,4520235768">全猪队友</d><d p="440.06300,1,25,16777215,1525734425,0,229a0a4,4520414474">竟然是yo no梗hhhhh</d><d p="1001.07800,1,25,16777215,1525737836,0,92012138,4520443021">不是每个微波炉都是一样的</d><d p="336.13300,1,25,16777215,1525738632,0,554f5363,4520451388">前方高能</d><d p="543.33200,1,25,15138834,1525755181,0,635bbb2a,4520789747">心疼妹子</d><d p="1158.64900,1,25,15138834,1525755956,0,635bbb2a,4520823148">应该是好人的</d><d p="444.08800,5,25,11890,1525758903,0,5bed8086,4520921310">杨永信</d><d p="388.26300,1,25,16777215,1525763803,0,2a0ed5aa,4521024661">乡愁？</d><d p="203.36000,1,25,16707842,1525779530,0,d546d497,4521554827">日本的有的鸡蛋可以生吃的</d><d p="222.60000,1,25,16707842,1525779554,0,d546d497,4521555751">嘟嘟噜</d><d p="235.60000,1,25,16707842,1525779585,0,d546d497,4521557043">桶子还是他爸呢(跑)</d><d p="901.74500,1,25,16777215,1525789141,0,812daf1,4521995951">感谢字幕君！</d><d p="36.14800,1,25,16777215,1525789997,0,5b33897c,4522042659">AA</d><d p="543.92400,1,25,38979,1525790802,0,bc994226,4522085547">花泽韭菜</d><d p="8.14800,1,25,16777215,1525802511,0,e7b785cc,4522500160">蝴蝶效应</d><d p="275.39000,1,25,16777215,1525802746,0,e7b785cc,4522503705">圆桌四骑士</d><d p="297.42700,1,25,16777215,1525802774,0,e7b785cc,4522504099">参见吾王</d><d p="366.82500,1,25,16777215,1525802869,0,e7b785cc,4522505424">亚瑟王叫阿尔托莉雅潘德拉贡</d><d p="445.69400,1,25,16777215,1525802951,0,e7b785cc,4522506526">嘟嘟噜</d><d p="560.95800,1,25,16777215,1525803075,0,e7b785cc,4522508221">百合大法好</d><d p="778.79300,1,25,16777215,1525803297,0,e7b785cc,4522511217">愉悦</d><d p="906.19600,1,25,16777215,1525803462,0,e7b785cc,4522513353">感谢字幕君</d><d p="982.27100,1,25,16777215,1525803546,0,e7b785cc,4522514388">嘟嘟噜</d><d p="160.41900,1,25,16777215,1525834291,0,85d3b424,4522794856">当成搞笑的看别有一番风味</d><d p="472.32700,1,25,16777215,1525847567,0,a9f83e3a,4523166482">啥子意思</d><d p="1314.39700,1,25,16777215,1525850414,0,1d5d77b7,4523223214">FUCK BOY</d><d p="721.10900,1,25,16777215,1525852689,0,6d8cf286,4523267905">这种终于意识到惹事了</d><d p="344.54600,1,25,16777215,1525854665,0,9a6c7daa,4523309374">阿福才是真爱。</d><d p="519.18700,1,25,16777215,1525860542,0,d75d031c,4523818138">花泽泡菜</d><d p="844.74400,1,25,16777215,1525865862,0,ed0b4b4e,4524016343">世纪性实验</d><d p="1304.22500,1,25,38979,1525866305,0,1506d645,4524033759">组织深层</d><d p="35.50000,1,25,16777215,1525867715,0,60182977,4524090062">上瘾了</d><d p="1056.99700,1,25,16777215,1525868697,0,60182977,4524130511">冲厕所……</d><d p="1089.79900,1,25,16777215,1525873544,0,8aea12c8,4524337218">2018五月二十五号</d><d p="266.15400,1,25,16777215,1525878992,0,4e63452a,4524594648">唔姆！</d><d p="501.50300,1,25,16777215,1525879291,0,4e63452a,4524608867">花泽芹菜</d><d p="559.68100,1,25,16777215,1525879406,0,4e63452a,4524614258">橘里橘气</d><d p="563.49800,1,25,16777215,1525879424,0,4e63452a,4524615101"> 唔姆</d><d p="715.67300,1,25,16777215,1525879762,0,4e63452a,4524630808">我是你的破壁人</d><d p="465.53500,5,25,15138834,1525880075,0,62ac43c,4524644848">那Emial？</d><d p="1035.73300,1,25,16777215,1525880217,0,4e63452a,4524651112">嗯，这个现象时间简史有讲，三体三也有提到</d><d p="1092.47900,1,25,16777215,1525880290,0,4e63452a,4524654289">注孤生</d><d p="951.11300,1,25,16777215,1525885072,0,8afad6ce,4524819897">233</d><d p="24.12000,1,25,16707842,1525888412,0,f0965fdb,4524885141">缩进被几瑟瑟发抖</d><d p="18.55800,1,25,16777215,1525889779,0,a5c72e77,4524903353">游戏上应该是叫[蝶翼的变动率]来着，，，</d><d p="57.17200,1,25,16777215,1525889867,0,a5c72e77,4524904422">这位不擅长与人直接对话，需要用短信的说</d><d p="151.25200,1,25,16777215,1525890005,0,a5c72e77,4524906044">我信</d><d p="814.25600,1,25,16777215,1525890718,0,a5c72e77,4524913848">嘛，也没准是未来发生过什么呢？</d><d p="1322.99000,1,25,16777215,1525891315,0,a5c72e77,4524919781">FB是啥你们应该很快就知道了</d><d p="1330.45700,1,25,16777215,1525891344,0,a5c72e77,4524920043">这其实是遗憾的表情</d><d p="826.46700,1,25,16777215,1525900886,0,2c001e76,4524973931">情敌见面分外眼红</d><d p="455.63500,5,25,16777215,1525928285,0,ad53db16,4525373524">G-back</d><d p="516.26500,5,25,16777215,1525928369,0,ad53db16,4525376893">别怕，我这里还有个大香蕉（滑稽）</d><d p="531.88100,5,25,16777215,1525928407,0,ad53db16,4525378309">花泽腊肉</d><d p="628.26500,5,25,16707842,1525928567,0,ad53db16,4525384416">冈部小辣鸡</d><d p="504.44600,1,25,16777215,1525928771,0,1dbac3a,4525392178">花泽生菜</d><d p="822.70200,5,25,16777215,1525928852,0,ad53db16,4525395278">胸震又开始了（滑稽）</d><d p="837.12600,5,25,16777215,1525928880,0,ad53db16,4525396284">我秃了，也变强了</d><d p="989.46400,5,25,16777215,1525929100,0,ad53db16,4525404297">ed开始</d><d p="1229.67800,5,25,16777215,1525929371,0,ad53db16,4525413753">糟糕的台词</d><d p="1314.28600,5,25,16777215,1525929469,0,ad53db16,4525417209">first banana</d><d p="933.37500,1,25,16777215,1525934490,0,337d0e03,4525540814">野生字幕是tips啊233  游戏的既视感</d><d p="469.07400,1,25,16777215,1525953807,0,c2e2c47,4526084782">diss mail 可还行</d><d p="725.44600,1,25,16777215,1525954077,0,c2e2c47,4526095379">残影？</d><d p="1301.54200,1,25,16777215,1525957948,0,88112965,4526254770">fuck bi~~~~?</d><d p="219.09000,1,25,16777215,1525965039,0,f6657e17,4526595351">six</d><d p="504.18900,5,25,16777215,1525968755,0,b0819ba,4526796859">Fa泽泡菜</d><d p="698.86200,1,25,16777215,1526019134,0,d16d8e08,4527657171">又开始中二了</d><d p="344.25500,1,25,16777215,1526020972,0,dd249aad,4527700308">Saber</d><d p="357.78500,1,25,16777215,1526020986,0,dd249aad,4527700641">Saber我的</d><d p="768.68200,1,25,16777215,1526036236,0,b4818180,4528292092">浮华</d><d p="841.83400,1,25,16777215,1526038146,0,436937dd,4528381427">是未来会发生什么吧</d><d p="907.05200,1,25,16777215,1526041022,0,2b46d320,4528520718">感谢野生字幕君</d><d p="376.53500,1,25,16777215,1526046666,0,8559e982,4528849078">欧蕾哇刚大木！</d><d p="719.94200,1,25,16777215,1526047017,0,8559e982,4528867980">god finger！</d><d p="827.24400,1,25,16777215,1526054105,0,ebd5b5b8,4529252528">打工战士超可爱</d><d p="695.42800,1,25,16777215,1526054581,0,c88701f1,4529275933">吓到的加一</d><d p="686.83100,1,25,16776960,1526065855,0,7c1adb99,4529579297">邪能</d><d p="366.28700,1,25,16777215,1526088161,0,190e48fd,4529845263">中二之魂在燃烧</d><d p="237.28700,1,25,16777215,1526099409,0,29533366,4530272102">嘟嘟噜真的洗脑</d><d p="885.71700,1,25,16777062,1526102705,0,edb79774,4530437327">邵东咋么了</d><d p="950.34600,1,25,16777062,1526102840,0,edb79774,4530443971">我来松松</d><d p="297.05200,1,25,16777215,1526105029,0,7c5dca67,4530546490">吾王剑之所指，吾等心之所向</d><d p="326.75000,1,25,16777215,1526105067,0,7c5dca67,4530548219">亚瑟王</d><d p="328.98000,1,25,16777215,1526105074,0,7c5dca67,4530548491">圆桌骑士团</d><d p="380.45800,1,25,16777215,1526105128,0,7c5dca67,4530550827">哈？</d><d p="760.91700,1,25,16777215,1526105517,0,7c5dca67,4530567384">emmm</d><d p="934.28500,1,25,16777215,1526106301,0,1044406c,4530600740">真是糟糕的台词</d><d p="666.63300,1,25,16777215,1526107610,0,98a0bf35,4530654720">是字符限制吗……？</d><d p="315.93600,1,25,16777215,1526108024,0,d963b0a4,4530671358">浪荡者的茶会</d><d p="276.59800,1,25,16777215,1526108943,0,78583065,4530708783">圆桌骑士</d><d p="381.87700,1,25,16777215,1526109061,0,78583065,4530713411">是时空旅行，不是跳跃</d><d p="18.58600,1,25,16777215,1526116616,0,f136ca6e,4531025498">就放那晾着是吗</d><d p="538.19600,1,25,16777215,1526118666,0,3e8755a6,4531123479">花泽地三鲜</d><d p="548.27100,1,25,16777215,1526118676,0,3e8755a6,4531123942">花泽烤冷面</d><d p="226.45300,1,25,14811775,1526119907,0,798665d,4531186621">嘟嘟噜</d><d p="297.79300,1,25,14811775,1526120456,0,798665d,4531214193">时臣：我已做好背锅准备，谁时可以开始！</d><d p="339.56100,1,25,16777215,1526121003,0,64675ac1,4531241084">啥集娃娃还敢称王</d><d p="509.26800,1,25,16777215,1526121194,0,64675ac1,4531250662">花泽大头菜</d><d p="115.79700,1,25,16777215,1526125203,0,45f7fb06,4531458526">铃羽我的</d><d p="1091.41000,1,25,9487136,1526142169,0,cd3b8541,4532448262">看过rewrite的毫无压力</d><d p="31.70000,5,25,15138834,1526142197,0,1b6de9cd,4532449528">稳住，我们能懂。</d><d p="259.95400,5,25,15138834,1526142451,0,1b6de9cd,4532461427">嘟嘟噜呢？我的嘟嘟噜呢？？？</d><d p="302.27400,5,25,15138834,1526142515,0,1b6de9cd,4532464335">吾王剑锋所指，吾等心之所向。</d><d p="783.80800,5,25,15138834,1526143023,0,1b6de9cd,4532487150">偷税</d><d p="904.00600,5,25,15138834,1526143212,0,1b6de9cd,4532495313">感谢野生字幕菌</d><d p="231.75500,1,25,16777215,1526143431,0,b7f90a7d,4532504683">好歹盖饭店老板娘是有画面最多的NPC了:(；ﾞﾟ'ωﾟ'):</d><d p="1270.39800,5,25,15138834,1526143593,0,1b6de9cd,4532511550">生无可恋</d><d p="378.23300,1,25,15138834,1526148671,0,96ebb6ee,4532676367">你是月山习</d><d p="378.23300,5,25,15138834,1526148692,0,96ebb6ee,4532676855">你是月山习</d><d p="378.23300,5,25,38979,1526148716,0,96ebb6ee,4532677387">你是月山习</d><d p="378.23300,5,25,41194,1526148730,0,96ebb6ee,4532677691">你是月山习</d><d p="378.23300,5,25,9487136,1526148741,0,96ebb6ee,4532677995">你是月山习</d><d p="378.23300,5,25,15772458,1526148757,0,96ebb6ee,4532678364">你是月山习</d><d p="901.31400,1,25,16777215,1526149309,0,2a3a8611,4532690428">感谢</d><d p="488.38400,1,25,16777215,1526162751,0,23fefcf4,4532820999">血魔人那个</d><d p="496.39100,1,25,16777215,1526162759,0,23fefcf4,4532821052">勾起了我童年</d><d p="800.75900,1,25,16777215,1526163063,0,23fefcf4,4532822963">哪像符华了</d><d p="936.16400,1,25,16777215,1526163212,0,23fefcf4,4532823940">.....................</d><d p="1265.36300,1,25,16777215,1526166491,0,cd4a1fda,4532854977">嘟嘟噜</d><d p="933.41200,5,25,15138834,1526168189,0,89ca19d7,4532878371">糟糕的台词</d><d p="1326.87800,1,25,16777215,1526175030,0,e72e32c1,4533058882">zero zero 狗蛋</d><d p="388.11500,1,25,41194,1526178176,0,5682404f,4533182426">中二癌晚期</d><d p="877.86000,1,25,16777215,1526191071,0,a568884,4533827646">开始了</d><d p="605.49500,1,25,16777215,1526199339,0,d7de4296,4534215447">没多次试验 具有偶然性 事实也确实如此</d><d p="861.73500,1,25,16777215,1526201694,0,19424424,4534320163">螺蛳粉</d><d p="242.41800,1,25,16777215,1526202298,0,71d07d30,4534347579">嘟嘟噜</d><d p="406.40200,1,25,16777215,1526202550,0,d5bb5b2f,4534358669">这个不是no总的ID吗</d><d p="855.69500,1,25,16777215,1526203359,0,db4f2121,4534394738">八重樱QAQ</d><d p="946.35200,1,25,16777215,1526203806,0,c78fd7be,4534414349">这胖子真有意思</d><d p="1311.75000,1,25,16777215,1526204816,0,184b9317,4534458731">至今没见过比凉宫和冰菓字幕组更良心的</d><d p="388.54700,1,25,16777215,1526204867,0,8fc9fcfe,4534460927">gn drive！trans am</d><d p="1003.48200,1,25,16777215,1526207491,0,9c22a7d5,4534573308">嘎威！</d><d p="1299.94500,1,25,16777215,1526207792,0,9c22a7d5,4534585987">F B I。。</d><d p="178.09900,1,25,16777215,1526212857,0,bfe87dc,4534804133">iphone11毫无压力</d><d p="1285.65900,1,25,16777215,1526215195,0,b7f90a7d,4534907519">(๑•ี_เ•ี๑)好像每次对着手机说的都成了真的</d><d p="936.03800,5,25,15138834,1526217188,0,4d7d23f7,4535000328">助手秒懂</d><d p="1025.78100,1,25,16777215,1526220283,0,e32590f6,4535155136">岂因祸福避趋之</d><d p="1122.29200,1,25,16777215,1526220446,0,e32590f6,4535163445">西方记者？？？</d><d p="520.17700,1,25,16777215,1526273809,0,913d1835,4536288152">花泽嘟嘟噜～</d><d p="639.53400,1,25,16777215,1526286765,0,29624e73,4536595845">意思是两条时间线？</d><d p="635.38700,1,25,16777215,1526299977,0,98509f1c,4537036131">因为时间机器传送量不够，所以被分成两条</d><d p="709.77700,1,25,16777215,1526300077,0,98509f1c,4537040188">面壁者肛轮，我是你的破壁人。</d><d p="177.96200,1,25,41194,1526305792,0,b6de307a,4537290520">埃尼阿克无压力</d><d p="175.64200,1,25,16777215,1526310385,0,e40352a8,4537528871">戴尔游匣无压力</d><d p="70.44000,1,25,16777215,1526311116,0,6698708a,4537565078">op超赞</d><d p="519.67900,1,25,16777215,1526313576,0,3b694b1b,4537677153">这胖子咋这浑呢</d><d p="251.30800,1,25,16777215,1526319860,0,5b6ac638,4537847881">桶子大号金闪闪</d><d p="995.46000,1,25,16777215,1526360213,0,f3e0b375,4538364635">标题bgm</d><d p="571.80400,1,25,16777215,1526362199,0,7407fa14,4538438237">华泽小杰</d><d p="1301.65600,1,25,16777215,1526362972,0,7407fa14,4538461507">flashback？</d><d p="1322.22600,1,25,16777215,1526363002,0,7407fa14,4538462281">泽拉泽拉狗蛋</d><d p="708.65000,1,25,38979,1526367521,0,117038d7,4538560898">恐怖</d><d p="1272.06700,5,25,16777215,1526373434,0,6f0a11a3,4538704224">凉凉</d><d p="23.89600,5,25,9487136,1526380766,0,1da3d948,4538908121">以为我手机振动呢。。。。</d><d p="757.66300,1,25,16777215,1526385190,0,72ba171b,4539070535">桐生一马</d><d p="1268.84200,1,25,16777215,1526401691,0,12cab79d,4539763959">凉了</d><d p="3.00200,5,25,16777215,1526443605,0,820ac981,4540284503">到第6话了我还是懵</d><d p="503.09500,5,25,16707842,1526447775,0,446d0217,4540448460">花泽芹菜</d></i>